README.md
setup.cfg
setup.py
django_editorjs_parser/__init__.py
django_editorjs_parser/config.py
django_editorjs_parser/helpers.py
django_editorjs_parser/parser.py
django_editorjs_parser/plugins.py
django_editorjs_parser.egg-info/PKG-INFO
django_editorjs_parser.egg-info/SOURCES.txt
django_editorjs_parser.egg-info/dependency_links.txt
django_editorjs_parser.egg-info/not-zip-safe
django_editorjs_parser.egg-info/top_level.txt