Metadata-Version: 2.1
Name: django-editorjs-parser
Version: 0.1.5
Summary: Parser for clean-blocks used by editor-js written in python
Home-page: https://github.com/giokast/python_editorjs_parser
Author: giovkast
Author-email: giovkast@gmail.com
License: MIT
Download-URL: https://github.com/giokast/django_editorjs_parser/archive/refs/tags/0.1.5.tar.gz
Platform: UNKNOWN
Classifier: Development Status :: 4 - Beta
Classifier: Intended Audience :: Developers
Classifier: Topic :: Software Development :: Build Tools
Classifier: License :: OSI Approved :: MIT License
Classifier: Programming Language :: Python :: 3
Classifier: Programming Language :: Python :: 3.4
Classifier: Programming Language :: Python :: 3.5
Classifier: Programming Language :: Python :: 3.6
